[{"coordinates":[{"lat":51.0832714,"lon":13.7306131}],"file_name":"00066578.pdf"},{"coordinates":[{"lat":51.1188236,"lon":13.7659144}],"file_name":"00065487.pdf"},{"coordinates":[{"lat":51.1188236,"lon":13.7659144}],"file_name":"00065126.pdf"},{"coordinates":[{"lat":51.0832714,"lon":13.7306131}],"file_name":"00066536.pdf"},{"coordinates":[{"lat":51.1188236,"lon":13.7659144}],"file_name":"00065129.pdf"},{"coordinates":[{"lat":51.0331076,"lon":13.7280773}],"file_name":"00066547.pdf"},{"coordinates":[{"lat":51.0085075,"lon":13.8259577},{"lat":51.0832714,"lon":13.7306131}],"file_name":"00069766.pdf"},{"coordinates":[{"lat":51.0307996,"lon":13.7813786},{"lat":51.0307996,"lon":13.7813786}],"file_name":"00065460.pdf"},{"coordinates":[{"lat":51.0307996,"lon":13.7813786},{"lat":51.0307996,"lon":13.7813786}],"file_name":"00065515.pdf"},{"coordinates":[{"lat":51.0085075,"lon":13.8259577}],"file_name":"00067042.pdf"},{"coordinates":[{"lat":51.1188236,"lon":13.7659144},{"lat":51.1129403,"lon":13.764204},{"lat":51.1220016,"lon":13.7628847}],"file_name":"00065130.pdf"},{"coordinates":[{"lat":51.0331076,"lon":13.7280773}],"file_name":"00071792.pdf"}]