{
  "id": "FL/067/2012",
  "description": "67. Sitzung des Ausschusses für Finanzen und Liegenschaften (Sondersitzung)",
  "committee": "Ausschuss für Finanzen und Liegenschaften",
  "started_at": "2012-11-05T14:00:00Z",
  "ended_at": "2012-11-05T15:25:00Z",
  "location": "Landeshauptstadt Dresden,  7. Etage, Raum 728,Ferdinandplatz 2, 01069 Dresden",
  "parts": [

  ],
  "documents": [
    {
      "file_name": "00113622.pdf",
      "description": "Einladung_FL_2012_11_05"
    }
  ],
  "downloaded_at": "2013-07-15T03:17:57Z",
  "session_url": "http://ratsinfo.dresden.de/to0040.php?__ksinr=2884"
}