{
  "id": "OBR Co/035/2013",
  "description": "35. Sitzung des Ortsbeirates Cotta",
  "committee": "Ortsbeirat Cotta",
  "started_at": "2013-06-06T16:00:00Z",
  "ended_at": "2013-06-06T18:35:00Z",
  "location": "Landeshauptstadt Dresden,  im Ortsamt Cotta, kleiner Sitzungssaal, 1. Etage, Raum 103,Lübecker Straße 121, 01157 Dresden",
  "parts": [
    {
      "description": "Begrüßung, Feststellung der Beschlussfähigkeit und Bestätigung der Tagesordnung",
      "template_id": " ",
      "documents": [

      ],
      "decision": null,
      "vote_result": null
    },
    {
      "description": "Bebauungsplan Nr. 373, Dresden-Löbtau Nr. 3, Gewerbe-Park Freiberger Straßehier:1. Beschluss über geänderten Geltungsbereich 2. Billigung des Entwurfs zum Bebauungsplan 3. Billigung der Begründung zum Bebauungsplan-Entwurf 4. Öffentliche Auslegung des Entwurfs zum Bebauungsplan",
      "template_id": "V2282/13",
      "documents": [
        {
          "description": "Beschlussausfertigung_SB",
          "file_name": "00137506.pdf"
        },
        {
          "description": "V2282/13",
          "file_name": "00133492.pdf"
        },
        {
          "description": "Vorlage Gremien",
          "file_name": "00133019.pdf"
        },
        {
          "description": "a) Anlage 1_Geltungsbereich",
          "file_name": "00132223.pdf"
        },
        {
          "description": "b) Anlage 2_Übersichtsplan",
          "file_name": "00132224.pdf"
        },
        {
          "description": "c) Anlage 3_Entwurf_rechtsplan-A3",
          "file_name": "00132225.pdf"
        },
        {
          "description": "d) Anlage 3_Entwurf_text-A3 lang",
          "file_name": "00132226.pdf"
        },
        {
          "description": "e) Anlage 4_Begründung Teil A",
          "file_name": "00132227.pdf"
        },
        {
          "description": "f) Anlage 4_Begründung Teil B_Umweltbericht",
          "file_name": "00132228.pdf"
        },
        {
          "description": "g) Anlage 4_Begründung Teil C_D",
          "file_name": "00132229.pdf"
        },
        {
          "description": "i) bereits gefasste Beschlüsse_V2282",
          "file_name": "00132234.pdf"
        }
      ],
      "decision": "Zustimmung",
      "vote_result": {
        "pro": " 18",
        "contra": " 0",
        "abstention": 0
      }
    },
    {
      "description": "Vorplanung Äußerer Stadtring West Hauptabschnitt 5, Hamburger Straße zwischen Warthaer Straße und Haltepunkt Cotta",
      "template_id": "V2241/13",
      "documents": [
        {
          "description": "V2241/13",
          "file_name": "00133487.pdf"
        },
        {
          "description": "Vorlage Gremien",
          "file_name": "00133025.pdf"
        },
        {
          "description": "a) Anlage 1_Übersichtsplan",
          "file_name": "00130571.pdf"
        },
        {
          "description": "b) Anlage 2_Lageplan",
          "file_name": "00130572.pdf"
        },
        {
          "description": "c) Anlage 3_Lageplan Alternativvariante",
          "file_name": "00130573.pdf"
        },
        {
          "description": "d) Anlage 4_Lageplanausschnitt Einfeldbrücke",
          "file_name": "00130574.pdf"
        },
        {
          "description": "e) Anlage 5_ Prinzipquerschnitte",
          "file_name": "00130575.pdf"
        },
        {
          "description": "f) bereits gefasste Beschlüsse",
          "file_name": "00130593.pdf"
        },
        {
          "description": "V2241-13-Stellungnahme BMB",
          "file_name": "00131258.pdf"
        }
      ],
      "decision": "Zustimmung",
      "vote_result": {
        "pro": " 18",
        "contra": " 0",
        "abstention": 0
      }
    },
    {
      "description": "Bürgerbeteiligung stärken – Einrichtung einer Plattform für E-Petitionen auf der Stadt-Website",
      "template_id": "A0722/13",
      "documents": [
        {
          "description": "Antrag GRÜNE",
          "file_name": "00129669.pdf"
        }
      ],
      "decision": "Ablehnung",
      "vote_result": {
        "pro": " 2",
        "contra": " 14",
        "abstention": 0
      }
    }
  ],
  "documents": [
    {
      "file_name": "00133332.pdf",
      "description": "Einladung_OBR Co"
    }
  ],
  "downloaded_at": "2013-07-15T03:54:24Z",
  "session_url": "http://ratsinfo.dresden.de/to0040.php?__ksinr=2781"
}