{
  "id": "ISF/012/2010",
  "description": "12. Sitzung des Betriebsausschusses für IT-Dienstleistungen, Stadtentwässerung und Friedhofswesen",
  "committee": "Betriebsausschuss für IT-Dienstleistungen, Stadtentwässerung und Friedhofswesen",
  "started_at": "2010-10-20T14:30:00Z",
  "ended_at": "2010-10-20T15:45:00Z",
  "location": "Landeshauptstadt Dresden,  im Neuen Rathaus, Beratungsraum 1, 1. Etage, Raum 13,Dr.-Külz-Ring 19, 01067 Dresden",
  "parts": [

  ],
  "documents": [
    {
      "file_name": "00044107.pdf",
      "description": "Einladung_ISF_2010_10_20"
    }
  ],
  "downloaded_at": "2013-07-15T01:14:01Z",
  "session_url": "http://ratsinfo.dresden.de/to0040.php?__ksinr=667"
}