{
  "id": "SG/046/2012",
  "description": "46. Sitzung des Ausschusses für Soziales, Gesundheit und Wohnen",
  "committee": "Ausschuss für Soziales, Gesundheit und Wohnen",
  "started_at": "2012-11-29T14:00:00Z",
  "ended_at": "2012-11-29T15:45:00Z",
  "location": "Landeshauptstadt Dresden,  im Neuen Rathaus, Beratungsraum 4, 4. Etage, Raum 13,Dr.-Külz-Ring 19, 01067 Dresden",
  "parts": [
    {
      "description": "Aufgaben und Tätigkeitsbericht der Beratungsstelle für AIDS und sexuell übertragbare Krankenheiten",
      "template_id": " ",
      "documents": [

      ],
      "decision": null,
      "vote_result": null
    }
  ],
  "documents": [
    {
      "file_name": "00116006.pdf",
      "description": "Einladung_SG"
    },
    {
      "file_name": "00118227.pdf",
      "description": "Niederschrift öffentlich"
    },
    {
      "file_name": "00118146.pdf",
      "description": "Anlage NS_ö_Vorstellung Beratungsstelle 2012"
    }
  ],
  "downloaded_at": "2013-07-15T03:22:48Z",
  "session_url": "http://ratsinfo.dresden.de/to0040.php?__ksinr=1768"
}