{
  "id": "OBR Neu/018/2011",
  "description": "18. Sitzung des Ortsbeirates Neustadt",
  "committee": "Ortsbeirat Neustadt",
  "started_at": "2011-04-18T15:30:00Z",
  "ended_at": "2011-04-18T20:45:00Z",
  "location": "Landeshauptstadt Dresden,  im Ortsamt Neustadt, Bürgersaal,Hoyerswerdaer Straße 3, 01099 Dresden",
  "parts": [
    {
      "description": "Anträge und Vorlagen zur Beratung und Berichterstattung an die Gremien des Stadtrates",
      "template_id": " ",
      "documents": [

      ],
      "decision": null,
      "vote_result": null
    },
    {
      "description": "Bereitstellung und Betreibung des Objektes Hechtstraße 10 als Übergangswohnheim mit 64 Plätzen für wohnungslose Dresdner Bürgerinnen und Bürger18:15 Uhr",
      "template_id": "V0834/10",
      "documents": [
        {
          "description": "Beschlussausfertigung_V0834/10",
          "file_name": "00063611.pdf"
        },
        {
          "description": "Vorlage Gremien",
          "file_name": "00051807.pdf"
        },
        {
          "description": "BK V0834/10 Abschlussbericht v. 2013-02-12",
          "file_name": "00123415.pdf"
        },
        {
          "description": "a_Anlage 1 Satzungsänderung",
          "file_name": "00051407.pdf"
        },
        {
          "description": "b_Beschlussausfertigung V2107",
          "file_name": "00047101.pdf"
        },
        {
          "description": "c_Beschlussausfertigung V1910",
          "file_name": "00047102.pdf"
        },
        {
          "description": "d_Beschlussausfertigung V0470",
          "file_name": "00047099.pdf"
        },
        {
          "description": "e_Beschlussausfertigung V0198",
          "file_name": "00047098.pdf"
        },
        {
          "description": "f_Beschlussausfertigung A0151",
          "file_name": "00047096.pdf"
        },
        {
          "description": "g_Stellungnahme GSB",
          "file_name": "00047524.pdf"
        }
      ],
      "decision": "Ablehnung",
      "vote_result": {
        "pro": " 0",
        "contra": " 0",
        "abstention": 0
      }
    },
    {
      "description": "Verordnung der Landeshauptstadt Dresden über das Offenhalten von Verkaufsstellen aus besonderem regionalen Anlass an Sonntagen im Jahr 2011",
      "template_id": "V1001/11",
      "documents": [
        {
          "description": "Beschlussausfertigung_V1001/11",
          "file_name": "00065610.pdf"
        },
        {
          "description": "Vorlage Gremien",
          "file_name": "00059609.pdf"
        },
        {
          "description": "VO regional",
          "file_name": "00061563.pdf"
        },
        {
          "description": "V1001/11",
          "file_name": "00059888.pdf"
        }
      ],
      "decision": "Zustimmung",
      "vote_result": {
        "pro": " 7",
        "contra": " 5",
        "abstention": 0
      }
    },
    {
      "description": "Fortschreibung des Integrierten Stadtentwicklungskonzeptes (INSEK 2002)",
      "template_id": "V0890/10",
      "documents": [
        {
          "description": "Beschlussausfertigung_V0890/10",
          "file_name": "00063656.pdf"
        },
        {
          "description": "Vorlage Gremien",
          "file_name": "00057703.pdf"
        },
        {
          "description": "BK V0890/10 Zwischenbericht v. 2012-12-05",
          "file_name": "00118556.pdf"
        }
      ],
      "decision": "zur Kenntnis genommen",
      "vote_result": null
    },
    {
      "description": "Kontrolle der Niederschrift zur 17. Ortsbeiratssitzung am 15.03.2011",
      "template_id": " ",
      "documents": [

      ],
      "decision": null,
      "vote_result": null
    }
  ],
  "documents": [
    {
      "file_name": "00059093.pdf",
      "description": "Einladung_OBR Neu"
    },
    {
      "file_name": "00061396.pdf",
      "description": "Niederschrift öffentlich_OBR Neu/18/2011"
    }
  ],
  "downloaded_at": "2013-07-15T01:40:43Z",
  "session_url": "http://ratsinfo.dresden.de/to0040.php?__ksinr=1308"
}