[{"coordinates":[{"lat":51.0324603,"lon":13.7850746}],"file_name":"00039638.pdf"},{"coordinates":[{"lat":51.0723466,"lon":13.6905811}],"file_name":"00027203.pdf"},{"coordinates":[{"lat":51.0324603,"lon":13.7850746}],"file_name":"00040156.pdf"},{"coordinates":[{"lat":51.0294001,"lon":13.7064775},{"lat":51.0261441,"lon":13.8352653}],"file_name":"00037863.pdf"},{"coordinates":[{"lat":51.0723466,"lon":13.6905811}],"file_name":"00027210.pdf"},{"coordinates":[{"lat":51.0294001,"lon":13.7064775},{"lat":51.0261441,"lon":13.8352653}],"file_name":"00027201.pdf"},{"coordinates":[{"lat":51.0723466,"lon":13.6905811}],"file_name":"00027209.pdf"},{"coordinates":[{"lat":51.0723466,"lon":13.6905811}],"file_name":"00028298.pdf"},{"coordinates":[{"lat":51.0547358,"lon":13.7193335}],"file_name":"00037803.pdf"},{"coordinates":[{"lat":51.0324603,"lon":13.7850746}],"file_name":"00037815.pdf"}]