{
  "id": "WF/030/2011",
  "description": "30. Sitzung des Ausschusses für Wirtschaftsförderung",
  "committee": "Ausschuss für Wirtschaftsförderung",
  "started_at": "2011-04-21T14:00:00Z",
  "ended_at": "2011-04-21T16:45:00Z",
  "location": "Landeshauptstadt Dresden,  im Neuen Rathaus, Beratungsraum 2, 2. Etage, Raum 13,Dr.-Külz-Ring 19, 01067 Dresden",
  "parts": [
    {
      "description": "Geschäftsbereich Finanzen und Liegenschaften",
      "template_id": " ",
      "documents": [

      ],
      "decision": null,
      "vote_result": null
    },
    {
      "description": "Vergabe-Nr.: A0009/10Neubau Zweifeldsporthalle mit Parkgeschoss am Gymnasium Dreikönigschule Art und Umfang der Leistung: Planungsleistungen gem. HOAI § 33 i. V. m. Anlage 11, Leistungsphasen 2 - 9",
      "template_id": "V1012/11",
      "documents": [
        {
          "description": "Beschlussausfertigung_V1012_11_WF",
          "file_name": "00061815.pdf"
        }
      ],
      "decision": "Zustimmung",
      "vote_result": {
        "pro": " 6",
        "contra": " 0",
        "abstention": 0
      }
    },
    {
      "description": "Vergabe-Nr.: 02.2/009/11Unterhalts-, Grund- und GlasreinigungBSZ für Technik, Gerokstraße 22, 01307 Dresden",
      "template_id": "V1021/11",
      "documents": [
        {
          "description": "Beschlussausfertigung_V1021_11_WF",
          "file_name": "00061819.pdf"
        }
      ],
      "decision": "Zustimmung",
      "vote_result": {
        "pro": " 11",
        "contra": " 0",
        "abstention": 0
      }
    },
    {
      "description": "Beschlussvorlagen zu VOB-Vergaben",
      "template_id": " ",
      "documents": [

      ],
      "decision": null,
      "vote_result": null
    },
    {
      "description": "Vergabe-Nr.: 5010/11Ausbau der Albertbrücke über die ElbeLos: 1, Bau einer Behelfsbrücke für Fußgänger und Radfahrer",
      "template_id": "V1024/11",
      "documents": [
        {
          "description": "Beschlussausfertigung_V1024_11_WF",
          "file_name": "00061834.pdf"
        }
      ],
      "decision": "Zustimmung",
      "vote_result": {
        "pro": " 11",
        "contra": " 0",
        "abstention": 0
      }
    },
    {
      "description": "Vergabe-Nr.: 5015/11Sanierungsgebiet S 10 Dresden-Neumarkt, Bauabschnitt E2Los: 1, Verkehrs- und Freianlagen",
      "template_id": "V1026/11",
      "documents": [
        {
          "description": "Beschlussausfertigung_V1026_11_WF",
          "file_name": "00061842.pdf"
        }
      ],
      "decision": "Zustimmung",
      "vote_result": {
        "pro": " 11",
        "contra": " 0",
        "abstention": 0
      }
    },
    {
      "description": "Vergabe-Nr.: 5026/11Zeitvertrag Gasrohrleitungsbauleistungen für Öffentliche Beleuchtung 2011 - 2014",
      "template_id": "V1028/11",
      "documents": [
        {
          "description": "Beschlussausfertigung_V1028_11_WF",
          "file_name": "00061851.pdf"
        }
      ],
      "decision": "Zustimmung",
      "vote_result": {
        "pro": " 11",
        "contra": " 0",
        "abstention": 0
      }
    }
  ],
  "documents": [
    {
      "file_name": "00060670.pdf",
      "description": "Einladung_WF_2011_04_21"
    },
    {
      "file_name": "00062196.pdf",
      "description": "Niederschrift öffentlich_WF_2011_04_21"
    }
  ],
  "downloaded_at": "2013-07-15T01:42:56Z",
  "session_url": "http://ratsinfo.dresden.de/to0040.php?__ksinr=1099"
}