{
  "id": "B/014/2012",
  "description": "14. Sitzung des Behindertenbeirates",
  "committee": "Behindertenbeirat",
  "started_at": "2012-12-12T15:00:00Z",
  "ended_at": "2012-12-12T16:15:00Z",
  "location": "Landeshauptstadt Dresden,  im Ortsamt Altstadt, 3. Etage, Raum 339,Theaterstraße 11, 01067 Dresden",
  "parts": [

  ],
  "documents": [
    {
      "file_name": "00117053.pdf",
      "description": "Einladung_B_2012_12_12"
    }
  ],
  "downloaded_at": "2013-07-15T03:23:19Z",
  "session_url": "http://ratsinfo.dresden.de/to0040.php?__ksinr=1872"
}