{
  "id": "OSR CB/025/2011",
  "description": "25. Sitzung des Ortschaftsrates Cossebaude",
  "committee": "Ortschaftsrat Cossebaude",
  "started_at": "2011-12-12T16:30:00Z",
  "ended_at": "2011-12-12T18:30:00Z",
  "location": "Landeshauptstadt Dresden,  im Bürgersaal der Verwaltungsstelle Cossebaude,Dresdner Straße 3, 01156 Dresden",
  "parts": [
    {
      "description": "Begrüßung und Feststellung der Beschlussfähigkeit",
      "template_id": " ",
      "documents": [

      ],
      "decision": null,
      "vote_result": null
    },
    {
      "description": "Einwohnerfragestunde",
      "template_id": " ",
      "documents": [

      ],
      "decision": null,
      "vote_result": null
    },
    {
      "description": "Fortschreibung der Schulnetzplanung, Planteile Grundschulen, Mittelschulen, Gymnasien, berufsbildende Schulen, Schulen des zweiten Bildungsweges und Schulen in nicht kommunaler Trägerschaft",
      "template_id": "V1282/11",
      "documents": [

      ],
      "decision": "Zustimmung",
      "vote_result": {
        "pro": " 10",
        "contra": " 0",
        "abstention": 0
      }
    }
  ],
  "documents": [
    {
      "file_name": "00081933.pdf",
      "description": "Einladung_OSR CB"
    },
    {
      "file_name": "00083529.pdf",
      "description": "Niederschrift öffentlich"
    }
  ],
  "downloaded_at": "2013-07-15T02:17:52Z",
  "session_url": "http://ratsinfo.dresden.de/to0040.php?__ksinr=1303"
}